nx2vos.py
nx2vos-0.2.dist-info/WHEEL
nx2vos-0.2.dist-info/METADATA
nx2vos-0.2.dist-info/RECORD
