Metadata-Version: 2.1
Name: nx2vos
Version: 0.2
Summary: nx2vos: export networkx graphs to VOSviewer format
Author-email: Raf Guns <raf.guns@uantwerpen.be>
Requires-Python: >=3.9
Classifier: Intended Audience :: Science/Research
Classifier: Intended Audience :: Developers
Classifier: License :: OSI Approved
Classifier: Programming Language :: Python :: 3.10
Classifier: Programming Language :: Python :: 3.11
Classifier: Programming Language :: Python :: 3.12
Classifier: Topic :: Software Development
Classifier: Topic :: Scientific/Engineering
Classifier: Development Status :: 4 - Beta
Classifier: Natural Language :: English
Classifier: Operating System :: OS Independent
Requires-Dist: networkx>=3.0
Requires-Dist: pytest >=7.1 ; extra == "dev"
Requires-Dist: pytest-cov ; extra == "dev"
Requires-Dist: pytest-unordered ; extra == "dev"
Requires-Dist: tox>=4.4 ; extra == "dev"
Project-URL: Home, https://github.com/rafguns/nx2vos/
Provides-Extra: dev
